lztyj/__init__.py
lztyj/lztyj.py
lztyj-0.0.1.dist-info/LICENSE
lztyj-0.0.1.dist-info/METADATA
lztyj-0.0.1.dist-info/WHEEL
lztyj-0.0.1.dist-info/top_level.txt
lztyj-0.0.1.dist-info/RECORD
