Metadata-Version: 2.1
Name: lztyj
Version: 0.0.1
Summary: print str lztyj
Author: lzt.tyj99
Author-email: lzt5120417@163.com
Requires-Python: >=3.6
License-File: LICENSE
